{
    "Objects": [
        {
            "name": "StaticObj_CementWorks_SiloBig1Bridge",
            "pos": [
                13379.087890625,
                67.30078887939453,
                12104.5361328125
            ],
            "ypr": [
                -90.00003814697266,
                0.0,
                -0.0
            ],
            "scale": 0.9999998807907105
        },
        {
            "name": "StaticObj_CementWorks_SiloBig1Bridge",
            "pos": [
                13379.1865234375,
                67.34346771240235,
                12087.4580078125
            ],
            "ypr": [
                -90.00003814697266,
                0.0,
                -0.0
            ],
            "scale": 0.9999998211860657
        },
        {
            "name": "StaticObj_CementWorks_SiloBig1Bridge",
            "pos": [
                13379.19921875,
                67.35260772705078,
                12072.728515625
            ],
            "ypr": [
                -90.00003814697266,
                0.0,
                -0.0
            ],
            "scale": 0.9999997615814209
        },
        {
            "name": "StaticObj_CementWorks_SiloBig1Bridge",
            "pos": [
                13379.2109375,
                67.320068359375,
                12055.3720703125
            ],
            "ypr": [
                -90.00003814697266,
                0.0,
                -0.0
            ],
            "scale": 0.9999995827674866
        },
        {
            "name": "Land_Tisy_RadarPlatform_Top",
            "pos": [
                13378.7548828125,
                61.32179641723633,
                12029.44921875
            ],
            "ypr": [
                -178.2108612060547,
                -0.0,
                -0.0
            ],
            "scale": 0.9999979734420776
        },
        {
            "name": "Land_Village_Pub",
            "pos": [
                13381.1708984375,
                72.59676361083985,
                12031.490234375
            ],
            "ypr": [
                -177.44473266601563,
                -0.0,
                -0.0
            ],
            "scale": 0.9999980926513672
        },
        {
            "name": "WoodenLog",
            "pos": [
                13367.95703125,
                68.5368881225586,
                12030.322265625
            ],
            "ypr": [
                4.48609733581543,
                -0.0,
                -0.0
            ],
            "scale": 0.9999984502792358
        },
        {
            "name": "WoodenLog",
            "pos": [
                13367.95703125,
                68.5368881225586,
                12030.322265625
            ],
            "ypr": [
                4.48609733581543,
                -0.0,
                -0.0
            ],
            "scale": 0.9999984502792358
        },
        {
            "name": "WoodenLog",
            "pos": [
                13367.95703125,
                68.5368881225586,
                12030.322265625
            ],
            "ypr": [
                4.48609733581543,
                -0.0,
                -0.0
            ],
            "scale": 0.9999984502792358
        },
        {
            "name": "WoodenLog",
            "pos": [
                13367.95703125,
                68.5368881225586,
                12030.322265625
            ],
            "ypr": [
                4.48609733581543,
                -0.0,
                -0.0
            ],
            "scale": 0.9999984502792358
        },
        {
            "name": "WoodenLog",
            "pos": [
                13367.95703125,
                68.5368881225586,
                12030.322265625
            ],
            "ypr": [
                4.48609733581543,
                -0.0,
                -0.0
            ],
            "scale": 0.9999984502792358
        },
        {
            "name": "WoodenLog",
            "pos": [
                13367.95703125,
                68.5368881225586,
                12030.322265625
            ],
            "ypr": [
                4.48609733581543,
                -0.0,
                -0.0
            ],
            "scale": 0.9999984502792358
        },
        {
            "name": "WoodenLog",
            "pos": [
                13367.95703125,
                68.5368881225586,
                12030.322265625
            ],
            "ypr": [
                4.48609733581543,
                -0.0,
                -0.0
            ],
            "scale": 0.9999984502792358
        },
        {
            "name": "WoodenLog",
            "pos": [
                13367.95703125,
                68.5368881225586,
                12030.322265625
            ],
            "ypr": [
                4.48609733581543,
                -0.0,
                -0.0
            ],
            "scale": 0.9999984502792358
        },
        {
            "name": "WoodenLog",
            "pos": [
                13367.95703125,
                68.5368881225586,
                12030.322265625
            ],
            "ypr": [
                4.48609733581543,
                -0.0,
                -0.0
            ],
            "scale": 0.9999984502792358
        },
        {
            "name": "WoodenLog",
            "pos": [
                13367.95703125,
                68.5368881225586,
                12030.322265625
            ],
            "ypr": [
                4.48609733581543,
                -0.0,
                -0.0
            ],
            "scale": 0.9999984502792358
        },
        {
            "name": "WoodenLog",
            "pos": [
                13367.95703125,
                68.5368881225586,
                12030.322265625
            ],
            "ypr": [
                4.48609733581543,
                -0.0,
                -0.0
            ],
            "scale": 0.9999984502792358
        },
        {
            "name": "WoodenLog",
            "pos": [
                13367.95703125,
                68.5368881225586,
                12030.322265625
            ],
            "ypr": [
                4.48609733581543,
                -0.0,
                -0.0
            ],
            "scale": 0.9999984502792358
        },
        {
            "name": "WoodenLog",
            "pos": [
                13367.95703125,
                68.5368881225586,
                12030.322265625
            ],
            "ypr": [
                4.48609733581543,
                -0.0,
                -0.0
            ],
            "scale": 0.9999984502792358
        },
        {
            "name": "WoodenLog",
            "pos": [
                13367.95703125,
                68.5368881225586,
                12030.322265625
            ],
            "ypr": [
                4.48609733581543,
                -0.0,
                -0.0
            ],
            "scale": 0.9999984502792358
        },
        {
            "name": "WoodenLog",
            "pos": [
                13367.95703125,
                68.5368881225586,
                12030.322265625
            ],
            "ypr": [
                4.48609733581543,
                -0.0,
                -0.0
            ],
            "scale": 0.9999984502792358
        },
        {
            "name": "WoodenLog",
            "pos": [
                13367.95703125,
                68.5368881225586,
                12030.322265625
            ],
            "ypr": [
                4.486117839813232,
                -0.0,
                -0.0
            ],
            "scale": 0.999998152256012
        },
        {
            "name": "WoodenLog",
            "pos": [
                13367.95703125,
                68.5368881225586,
                12030.322265625
            ],
            "ypr": [
                4.48609733581543,
                -0.0,
                -0.0
            ],
            "scale": 0.9999984502792358
        },
        {
            "name": "WoodenLog",
            "pos": [
                13367.95703125,
                68.5368881225586,
                12030.322265625
            ],
            "ypr": [
                4.48609733581543,
                -0.0,
                -0.0
            ],
            "scale": 0.9999984502792358
        },
        {
            "name": "WoodenLog",
            "pos": [
                13367.95703125,
                68.5368881225586,
                12030.322265625
            ],
            "ypr": [
                4.48609733581543,
                -0.0,
                -0.0
            ],
            "scale": 0.9999984502792358
        },
        {
            "name": "WoodenLog",
            "pos": [
                13367.95703125,
                68.5368881225586,
                12030.322265625
            ],
            "ypr": [
                4.48609733581543,
                -0.0,
                -0.0
            ],
            "scale": 0.9999984502792358
        },
        {
            "name": "WoodenLog",
            "pos": [
                13367.95703125,
                68.5368881225586,
                12030.322265625
            ],
            "ypr": [
                4.486022472381592,
                0.0,
                0.0
            ],
            "scale": 0.9999979138374329
        },
        {
            "name": "WoodenLog",
            "pos": [
                13367.95703125,
                68.5368881225586,
                12030.322265625
            ],
            "ypr": [
                4.48609733581543,
                -0.0,
                -0.0
            ],
            "scale": 0.9999984502792358
        },
        {
            "name": "WoodenLog",
            "pos": [
                13367.95703125,
                68.5368881225586,
                12030.322265625
            ],
            "ypr": [
                4.48609733581543,
                -0.0,
                -0.0
            ],
            "scale": 0.9999984502792358
        },
        {
            "name": "WoodenLog",
            "pos": [
                13367.95703125,
                68.5368881225586,
                12030.322265625
            ],
            "ypr": [
                4.48609733581543,
                -0.0,
                -0.0
            ],
            "scale": 0.9999984502792358
        },
        {
            "name": "WoodenLog",
            "pos": [
                13367.95703125,
                68.5368881225586,
                12030.322265625
            ],
            "ypr": [
                4.48609733581543,
                -0.0,
                -0.0
            ],
            "scale": 0.9999984502792358
        },
        {
            "name": "WoodenLog",
            "pos": [
                13367.95703125,
                68.5368881225586,
                12030.322265625
            ],
            "ypr": [
                4.48609733581543,
                -0.0,
                -0.0
            ],
            "scale": 0.9999984502792358
        },
        {
            "name": "WoodenLog",
            "pos": [
                13367.95703125,
                68.5368881225586,
                12030.322265625
            ],
            "ypr": [
                4.48609733581543,
                -0.0,
                -0.0
            ],
            "scale": 0.9999984502792358
        },
        {
            "name": "WoodenLog",
            "pos": [
                13367.95703125,
                68.5368881225586,
                12030.322265625
            ],
            "ypr": [
                4.48609733581543,
                -0.0,
                -0.0
            ],
            "scale": 0.9999984502792358
        },
        {
            "name": "WoodenLog",
            "pos": [
                13367.95703125,
                68.5368881225586,
                12030.322265625
            ],
            "ypr": [
                4.48609733581543,
                -0.0,
                -0.0
            ],
            "scale": 0.9999984502792358
        },
        {
            "name": "WoodenLog",
            "pos": [
                13367.95703125,
                68.5368881225586,
                12030.322265625
            ],
            "ypr": [
                4.48609733581543,
                -0.0,
                -0.0
            ],
            "scale": 0.9999984502792358
        },
        {
            "name": "WoodenLog",
            "pos": [
                13367.95703125,
                68.5368881225586,
                12030.322265625
            ],
            "ypr": [
                4.48609733581543,
                -0.0,
                -0.0
            ],
            "scale": 0.9999984502792358
        },
        {
            "name": "WoodenLog",
            "pos": [
                13367.95703125,
                68.5368881225586,
                12030.322265625
            ],
            "ypr": [
                4.48609733581543,
                -0.0,
                -0.0
            ],
            "scale": 0.9999984502792358
        },
        {
            "name": "WoodenLog",
            "pos": [
                13367.95703125,
                68.5368881225586,
                12030.322265625
            ],
            "ypr": [
                4.48609733581543,
                -0.0,
                -0.0
            ],
            "scale": 0.9999984502792358
        },
        {
            "name": "WoodenLog",
            "pos": [
                13367.95703125,
                68.5368881225586,
                12030.322265625
            ],
            "ypr": [
                4.48609733581543,
                -0.0,
                -0.0
            ],
            "scale": 0.9999984502792358
        },
        {
            "name": "WoodenLog",
            "pos": [
                13367.95703125,
                68.5368881225586,
                12030.322265625
            ],
            "ypr": [
                4.48609733581543,
                -0.0,
                -0.0
            ],
            "scale": 0.9999984502792358
        },
        {
            "name": "WoodenLog",
            "pos": [
                13367.95703125,
                68.5368881225586,
                12030.322265625
            ],
            "ypr": [
                4.48609733581543,
                -0.0,
                -0.0
            ],
            "scale": 0.9999984502792358
        },
        {
            "name": "WoodenLog",
            "pos": [
                13367.95703125,
                68.5368881225586,
                12030.322265625
            ],
            "ypr": [
                4.48609733581543,
                -0.0,
                -0.0
            ],
            "scale": 0.9999984502792358
        },
        {
            "name": "PileOfWoodenPlanks",
            "pos": [
                13375.787109375,
                68.39678192138672,
                12030.4814453125
            ],
            "ypr": [
                -85.51355743408203,
                0.0,
                0.0
            ],
            "scale": 0.9999983310699463
        },
        {
            "name": "PileOfWoodenPlanks",
            "pos": [
                13376.0830078125,
                68.4123764038086,
                12034.482421875
            ],
            "ypr": [
                -85.51361846923828,
                0.0,
                0.0
            ],
            "scale": 0.999998152256012
        },
        {
            "name": "MetalPlate",
            "pos": [
                13368.2109375,
                68.62598419189453,
                12018.822265625
            ],
            "ypr": [
                -3.720102548599243,
                -0.0,
                -0.0
            ],
            "scale": 0.9999947547912598
        },
        {
            "name": "MetalPlate",
            "pos": [
                13368.2109375,
                68.62598419189453,
                12018.822265625
            ],
            "ypr": [
                -3.720102548599243,
                -0.0,
                -0.0
            ],
            "scale": 0.9999947547912598
        },
        {
            "name": "MetalPlate",
            "pos": [
                13368.2109375,
                68.62598419189453,
                12018.822265625
            ],
            "ypr": [
                -3.720102548599243,
                -0.0,
                -0.0
            ],
            "scale": 0.9999947547912598
        },
        {
            "name": "MetalPlate",
            "pos": [
                13368.2109375,
                68.62598419189453,
                12018.822265625
            ],
            "ypr": [
                -3.720102548599243,
                -0.0,
                -0.0
            ],
            "scale": 0.9999947547912598
        },
        {
            "name": "MetalPlate",
            "pos": [
                13368.2109375,
                68.62598419189453,
                12018.822265625
            ],
            "ypr": [
                -3.720102548599243,
                -0.0,
                -0.0
            ],
            "scale": 0.9999947547912598
        },
        {
            "name": "MetalPlate",
            "pos": [
                13368.2109375,
                68.62598419189453,
                12018.822265625
            ],
            "ypr": [
                -3.720102548599243,
                -0.0,
                -0.0
            ],
            "scale": 0.9999947547912598
        },
        {
            "name": "MetalPlate",
            "pos": [
                13368.2109375,
                68.62598419189453,
                12018.822265625
            ],
            "ypr": [
                -3.720102548599243,
                -0.0,
                -0.0
            ],
            "scale": 0.9999947547912598
        },
        {
            "name": "MetalPlate",
            "pos": [
                13368.2109375,
                68.62598419189453,
                12018.822265625
            ],
            "ypr": [
                -3.720102548599243,
                -0.0,
                -0.0
            ],
            "scale": 0.9999947547912598
        },
        {
            "name": "MetalPlate",
            "pos": [
                13368.2109375,
                68.62598419189453,
                12018.822265625
            ],
            "ypr": [
                -3.720120429992676,
                -0.0,
                -0.0
            ],
            "scale": 0.9999974966049194
        },
        {
            "name": "Land_Garage_Tall",
            "pos": [
                13373.373046875,
                71.9222183227539,
                12045.6806640625
            ],
            "ypr": [
                -179.01519775390626,
                0.0,
                -0.0
            ],
            "scale": 0.999998927116394
        },
        {
            "name": "WoodenLog",
            "pos": [
                13367.95703125,
                68.5368881225586,
                12030.322265625
            ],
            "ypr": [
                4.48609733581543,
                -0.0,
                -0.0
            ],
            "scale": 0.9999984502792358
        },
        {
            "name": "Land_Roadblock_Table",
            "pos": [
                13367.48828125,
                69.07769012451172,
                12013.6357421875
            ],
            "ypr": [
                -90.23267364501953,
                -0.0,
                -0.0
            ],
            "scale": 0.9999937415122986
        },
        {
            "name": "Hatchet",
            "pos": [
                13367.224609375,
                69.5752182006836,
                12014.3203125
            ],
            "ypr": [
                -126.23270416259766,
                -0.0,
                -0.0
            ],
            "scale": 0.9999945163726807
        },
        {
            "name": "Hatchet",
            "pos": [
                13367.224609375,
                69.5752182006836,
                12014.3203125
            ],
            "ypr": [
                -126.23270416259766,
                -0.0,
                -0.0
            ],
            "scale": 0.9999945163726807
        },
        {
            "name": "Hatchet",
            "pos": [
                13367.224609375,
                69.5752182006836,
                12014.3203125
            ],
            "ypr": [
                -126.23270416259766,
                -0.0,
                -0.0
            ],
            "scale": 0.9999945163726807
        },
        {
            "name": "Hatchet",
            "pos": [
                13367.224609375,
                69.5752182006836,
                12014.3203125
            ],
            "ypr": [
                -126.23270416259766,
                -0.0,
                -0.0
            ],
            "scale": 0.9999945163726807
        },
        {
            "name": "Hatchet",
            "pos": [
                13367.224609375,
                69.5752182006836,
                12014.3203125
            ],
            "ypr": [
                -126.23270416259766,
                -0.0,
                -0.0
            ],
            "scale": 0.9999945163726807
        },
        {
            "name": "Hatchet",
            "pos": [
                13367.224609375,
                69.5752182006836,
                12014.3203125
            ],
            "ypr": [
                -126.23270416259766,
                -0.0,
                -0.0
            ],
            "scale": 0.9999945163726807
        },
        {
            "name": "Hatchet",
            "pos": [
                13367.224609375,
                69.5752182006836,
                12014.3203125
            ],
            "ypr": [
                -126.23270416259766,
                -0.0,
                -0.0
            ],
            "scale": 0.9999945163726807
        },
        {
            "name": "Hatchet",
            "pos": [
                13367.224609375,
                69.5719223022461,
                12014.3203125
            ],
            "ypr": [
                -126.23270416259766,
                -0.0,
                -0.0
            ],
            "scale": 0.9999945163726807
        },
        {
            "name": "NailBox",
            "pos": [
                13367.494140625,
                69.51680755615235,
                12014.0732421875
            ],
            "ypr": [
                -126.23270416259766,
                -0.0,
                -0.0
            ],
            "scale": 0.9999945163726807
        },
        {
            "name": "NailBox",
            "pos": [
                13367.494140625,
                69.51680755615235,
                12014.0732421875
            ],
            "ypr": [
                -126.23270416259766,
                -0.0,
                -0.0
            ],
            "scale": 0.9999945163726807
        },
        {
            "name": "NailBox",
            "pos": [
                13367.494140625,
                69.51680755615235,
                12014.0732421875
            ],
            "ypr": [
                -126.23270416259766,
                -0.0,
                -0.0
            ],
            "scale": 0.9999945163726807
        },
        {
            "name": "NailBox",
            "pos": [
                13367.494140625,
                69.51680755615235,
                12014.0732421875
            ],
            "ypr": [
                -126.23270416259766,
                -0.0,
                -0.0
            ],
            "scale": 0.9999945163726807
        },
        {
            "name": "NailBox",
            "pos": [
                13367.494140625,
                69.51680755615235,
                12014.0732421875
            ],
            "ypr": [
                -126.23270416259766,
                -0.0,
                -0.0
            ],
            "scale": 0.9999945163726807
        },
        {
            "name": "NailBox",
            "pos": [
                13367.494140625,
                69.51680755615235,
                12014.0732421875
            ],
            "ypr": [
                -126.23270416259766,
                -0.0,
                -0.0
            ],
            "scale": 0.9999945163726807
        },
        {
            "name": "NailBox",
            "pos": [
                13367.494140625,
                69.51680755615235,
                12014.0732421875
            ],
            "ypr": [
                -126.23270416259766,
                -0.0,
                -0.0
            ],
            "scale": 0.9999945163726807
        },
        {
            "name": "NailBox",
            "pos": [
                13367.494140625,
                69.51680755615235,
                12014.0732421875
            ],
            "ypr": [
                -126.23270416259766,
                -0.0,
                -0.0
            ],
            "scale": 0.9999945163726807
        },
        {
            "name": "HandSaw",
            "pos": [
                13367.7080078125,
                69.4959945678711,
                12014.1357421875
            ],
            "ypr": [
                -126.23270416259766,
                -0.0,
                -0.0
            ],
            "scale": 0.9999945163726807
        },
        {
            "name": "HandSaw",
            "pos": [
                13367.7080078125,
                69.4959945678711,
                12014.1357421875
            ],
            "ypr": [
                -126.23270416259766,
                -0.0,
                -0.0
            ],
            "scale": 0.9999945163726807
        },
        {
            "name": "HandSaw",
            "pos": [
                13367.7080078125,
                69.4959945678711,
                12014.1357421875
            ],
            "ypr": [
                -126.23270416259766,
                -0.0,
                -0.0
            ],
            "scale": 0.9999945163726807
        },
        {
            "name": "HandSaw",
            "pos": [
                13367.7080078125,
                69.4959945678711,
                12014.1357421875
            ],
            "ypr": [
                -126.23270416259766,
                -0.0,
                -0.0
            ],
            "scale": 0.9999945163726807
        },
        {
            "name": "HandSaw",
            "pos": [
                13367.7080078125,
                69.4959945678711,
                12014.1357421875
            ],
            "ypr": [
                -126.23270416259766,
                -0.0,
                -0.0
            ],
            "scale": 0.9999945163726807
        },
        {
            "name": "HandSaw",
            "pos": [
                13367.7080078125,
                69.4959945678711,
                12014.1357421875
            ],
            "ypr": [
                -126.23270416259766,
                -0.0,
                -0.0
            ],
            "scale": 0.9999945163726807
        },
        {
            "name": "HandSaw",
            "pos": [
                13367.7080078125,
                69.4959945678711,
                12014.1357421875
            ],
            "ypr": [
                -126.23270416259766,
                -0.0,
                -0.0
            ],
            "scale": 0.9999945163726807
        },
        {
            "name": "Shovel",
            "pos": [
                13367.3984375,
                69.25923919677735,
                12013.16796875
            ],
            "ypr": [
                -61.43273162841797,
                -0.0,
                -0.0
            ],
            "scale": 0.9999934434890747
        },
        {
            "name": "Shovel",
            "pos": [
                13367.47265625,
                69.3722152709961,
                12012.875
            ],
            "ypr": [
                -61.43273162841797,
                -0.0,
                -0.0
            ],
            "scale": 0.9999934434890747
        },
        {
            "name": "Shovel",
            "pos": [
                13367.47265625,
                69.3722152709961,
                12012.875
            ],
            "ypr": [
                -61.43273162841797,
                -0.0,
                -0.0
            ],
            "scale": 0.9999934434890747
        },
        {
            "name": "Shovel",
            "pos": [
                13367.47265625,
                69.3722152709961,
                12012.875
            ],
            "ypr": [
                -61.43273162841797,
                -0.0,
                -0.0
            ],
            "scale": 0.9999934434890747
        },
        {
            "name": "Shovel",
            "pos": [
                13367.47265625,
                69.3722152709961,
                12012.875
            ],
            "ypr": [
                -61.43273162841797,
                -0.0,
                -0.0
            ],
            "scale": 0.9999934434890747
        },
        {
            "name": "SledgeHammer",
            "pos": [
                13367.7294921875,
                69.53704071044922,
                12013.908203125
            ],
            "ypr": [
                -126.23270416259766,
                -0.0,
                -0.0
            ],
            "scale": 0.9999945163726807
        },
        {
            "name": "SledgeHammer",
            "pos": [
                13367.7294921875,
                69.53704071044922,
                12013.908203125
            ],
            "ypr": [
                -126.23270416259766,
                -0.0,
                -0.0
            ],
            "scale": 0.9999945163726807
        },
        {
            "name": "SledgeHammer",
            "pos": [
                13367.7294921875,
                69.53704071044922,
                12013.908203125
            ],
            "ypr": [
                -126.23270416259766,
                -0.0,
                -0.0
            ],
            "scale": 0.9999945163726807
        },
        {
            "name": "SledgeHammer",
            "pos": [
                13367.7294921875,
                69.53704071044922,
                12013.908203125
            ],
            "ypr": [
                -126.23270416259766,
                -0.0,
                -0.0
            ],
            "scale": 0.9999945163726807
        },
        {
            "name": "SledgeHammer",
            "pos": [
                13367.7294921875,
                69.53704071044922,
                12013.908203125
            ],
            "ypr": [
                -126.23270416259766,
                -0.0,
                -0.0
            ],
            "scale": 0.9999945163726807
        },
        {
            "name": "SledgeHammer",
            "pos": [
                13367.7294921875,
                69.53704071044922,
                12013.908203125
            ],
            "ypr": [
                -126.23270416259766,
                -0.0,
                -0.0
            ],
            "scale": 0.9999945163726807
        },
        {
            "name": "SledgeHammer",
            "pos": [
                13367.7294921875,
                69.53704071044922,
                12013.908203125
            ],
            "ypr": [
                -126.23270416259766,
                -0.0,
                -0.0
            ],
            "scale": 0.9999945163726807
        },
        {
            "name": "NailBox",
            "pos": [
                13367.494140625,
                69.51680755615235,
                12014.0732421875
            ],
            "ypr": [
                -126.23270416259766,
                -0.0,
                -0.0
            ],
            "scale": 0.9999945163726807
        },
        {
            "name": "NailBox",
            "pos": [
                13367.494140625,
                69.51680755615235,
                12014.0732421875
            ],
            "ypr": [
                -126.23270416259766,
                -0.0,
                -0.0
            ],
            "scale": 0.9999945163726807
        },
        {
            "name": "NailBox",
            "pos": [
                13367.494140625,
                69.51680755615235,
                12014.0732421875
            ],
            "ypr": [
                -126.23270416259766,
                -0.0,
                -0.0
            ],
            "scale": 0.9999945163726807
        },
        {
            "name": "NailBox",
            "pos": [
                13367.494140625,
                69.51680755615235,
                12014.0732421875
            ],
            "ypr": [
                -126.23270416259766,
                -0.0,
                -0.0
            ],
            "scale": 0.9999945163726807
        },
        {
            "name": "NailBox",
            "pos": [
                13367.494140625,
                69.51680755615235,
                12014.0732421875
            ],
            "ypr": [
                -126.23270416259766,
                -0.0,
                -0.0
            ],
            "scale": 0.9999945163726807
        },
        {
            "name": "NailBox",
            "pos": [
                13367.494140625,
                69.51680755615235,
                12014.0732421875
            ],
            "ypr": [
                -126.23270416259766,
                -0.0,
                -0.0
            ],
            "scale": 0.9999945163726807
        },
        {
            "name": "NailBox",
            "pos": [
                13367.494140625,
                69.51680755615235,
                12014.0732421875
            ],
            "ypr": [
                -126.23270416259766,
                -0.0,
                -0.0
            ],
            "scale": 0.9999945163726807
        },
        {
            "name": "NailBox",
            "pos": [
                13367.494140625,
                69.51680755615235,
                12014.0732421875
            ],
            "ypr": [
                -126.23270416259766,
                -0.0,
                -0.0
            ],
            "scale": 0.9999945163726807
        },
        {
            "name": "NailBox",
            "pos": [
                13367.494140625,
                69.51680755615235,
                12014.0732421875
            ],
            "ypr": [
                -126.23270416259766,
                -0.0,
                -0.0
            ],
            "scale": 0.9999945163726807
        },
        {
            "name": "NailBox",
            "pos": [
                13367.494140625,
                69.51680755615235,
                12014.0732421875
            ],
            "ypr": [
                -126.23270416259766,
                -0.0,
                -0.0
            ],
            "scale": 0.9999945163726807
        },
        {
            "name": "NailBox",
            "pos": [
                13367.494140625,
                69.51680755615235,
                12014.0732421875
            ],
            "ypr": [
                -126.23270416259766,
                -0.0,
                -0.0
            ],
            "scale": 0.9999945163726807
        },
        {
            "name": "MetalWire",
            "pos": [
                13367.5029296875,
                69.64717864990235,
                12014.748046875
            ],
            "ypr": [
                -63.23277282714844,
                -0.0,
                -0.0
            ],
            "scale": 0.9999943971633911
        },
        {
            "name": "Land_Roadblock_Table",
            "pos": [
                13367.474609375,
                69.09651947021485,
                12015.513671875
            ],
            "ypr": [
                -90.23267364501953,
                -0.0,
                -0.0
            ],
            "scale": 0.9999937415122986
        },
        {
            "name": "MetalWire",
            "pos": [
                13367.5029296875,
                69.64717864990235,
                12014.748046875
            ],
            "ypr": [
                -63.23277282714844,
                -0.0,
                -0.0
            ],
            "scale": 0.9999943971633911
        },
        {
            "name": "MetalWire",
            "pos": [
                13367.5029296875,
                69.64717864990235,
                12014.748046875
            ],
            "ypr": [
                -63.23277282714844,
                -0.0,
                -0.0
            ],
            "scale": 0.9999943971633911
        },
        {
            "name": "MetalWire",
            "pos": [
                13367.5029296875,
                69.64717864990235,
                12014.748046875
            ],
            "ypr": [
                -63.23277282714844,
                -0.0,
                -0.0
            ],
            "scale": 0.9999943971633911
        },
        {
            "name": "MetalWire",
            "pos": [
                13367.5029296875,
                69.64717864990235,
                12014.748046875
            ],
            "ypr": [
                -63.23277282714844,
                -0.0,
                -0.0
            ],
            "scale": 0.9999943971633911
        },
        {
            "name": "MetalWire",
            "pos": [
                13367.5029296875,
                69.64717864990235,
                12014.748046875
            ],
            "ypr": [
                -63.23277282714844,
                -0.0,
                -0.0
            ],
            "scale": 0.9999943971633911
        },
        {
            "name": "MetalWire",
            "pos": [
                13367.5029296875,
                69.64717864990235,
                12014.748046875
            ],
            "ypr": [
                -63.23277282714844,
                -0.0,
                -0.0
            ],
            "scale": 0.9999943971633911
        },
        {
            "name": "BarbedWire",
            "pos": [
                13367.6328125,
                69.59136199951172,
                12015.279296875
            ],
            "ypr": [
                -126.23270416259766,
                -0.0,
                -0.0
            ],
            "scale": 0.9999945163726807
        },
        {
            "name": "BarbedWire",
            "pos": [
                13367.6328125,
                69.59136199951172,
                12015.279296875
            ],
            "ypr": [
                -126.23270416259766,
                -0.0,
                -0.0
            ],
            "scale": 0.9999945163726807
        },
        {
            "name": "BarbedWire",
            "pos": [
                13367.6328125,
                69.59136199951172,
                12015.279296875
            ],
            "ypr": [
                -126.23270416259766,
                -0.0,
                -0.0
            ],
            "scale": 0.9999945163726807
        },
        {
            "name": "BarbedWire",
            "pos": [
                13367.6328125,
                69.59136199951172,
                12015.279296875
            ],
            "ypr": [
                -126.23270416259766,
                -0.0,
                -0.0
            ],
            "scale": 0.9999945163726807
        },
        {
            "name": "BarbedWire",
            "pos": [
                13367.6328125,
                69.59136199951172,
                12015.279296875
            ],
            "ypr": [
                -126.23270416259766,
                -0.0,
                -0.0
            ],
            "scale": 0.9999945163726807
        },
        {
            "name": "BarbedWire",
            "pos": [
                13367.6328125,
                69.59136199951172,
                12015.279296875
            ],
            "ypr": [
                -126.23270416259766,
                -0.0,
                -0.0
            ],
            "scale": 0.9999945163726807
        },
        {
            "name": "BarbedWire",
            "pos": [
                13367.6328125,
                69.59136199951172,
                12015.279296875
            ],
            "ypr": [
                -126.23270416259766,
                -0.0,
                -0.0
            ],
            "scale": 0.9999945163726807
        },
        {
            "name": "BarbedWire",
            "pos": [
                13367.6328125,
                69.59136199951172,
                12015.279296875
            ],
            "ypr": [
                -126.23270416259766,
                -0.0,
                -0.0
            ],
            "scale": 0.9999945163726807
        },
        {
            "name": "BarbedWire",
            "pos": [
                13367.6328125,
                69.59136199951172,
                12015.279296875
            ],
            "ypr": [
                -126.23270416259766,
                -0.0,
                -0.0
            ],
            "scale": 0.9999945163726807
        },
        {
            "name": "BarbedWire",
            "pos": [
                13367.6328125,
                69.59136199951172,
                12015.279296875
            ],
            "ypr": [
                -126.23268127441406,
                -0.0,
                -0.0
            ],
            "scale": 0.9999953508377075
        },
        {
            "name": "Rope",
            "pos": [
                13367.4208984375,
                69.63707733154297,
                12015.7060546875
            ],
            "ypr": [
                -126.23270416259766,
                -0.0,
                -0.0
            ],
            "scale": 0.9999945163726807
        },
        {
            "name": "Rope",
            "pos": [
                13367.4208984375,
                69.63707733154297,
                12015.7060546875
            ],
            "ypr": [
                -126.23270416259766,
                -0.0,
                -0.0
            ],
            "scale": 0.9999945163726807
        },
        {
            "name": "Rope",
            "pos": [
                13367.4208984375,
                69.63707733154297,
                12015.7060546875
            ],
            "ypr": [
                -126.23270416259766,
                -0.0,
                -0.0
            ],
            "scale": 0.9999945163726807
        },
        {
            "name": "Rope",
            "pos": [
                13367.4208984375,
                69.63707733154297,
                12015.7060546875
            ],
            "ypr": [
                -126.23270416259766,
                -0.0,
                -0.0
            ],
            "scale": 0.9999945163726807
        },
        {
            "name": "Rope",
            "pos": [
                13367.4208984375,
                69.63707733154297,
                12015.7060546875
            ],
            "ypr": [
                -126.23270416259766,
                -0.0,
                -0.0
            ],
            "scale": 0.9999945163726807
        },
        {
            "name": "Rope",
            "pos": [
                13367.4208984375,
                69.63707733154297,
                12015.7060546875
            ],
            "ypr": [
                -126.23270416259766,
                -0.0,
                -0.0
            ],
            "scale": 0.9999945163726807
        },
        {
            "name": "Rope",
            "pos": [
                13367.4208984375,
                69.63707733154297,
                12015.7060546875
            ],
            "ypr": [
                -126.23257446289063,
                -0.0,
                -0.0
            ],
            "scale": 0.9999967813491821
        },
        {
            "name": "Stone",
            "pos": [
                13367.509765625,
                68.72920989990235,
                12018.1142578125
            ],
            "ypr": [
                -126.23270416259766,
                -0.0,
                -0.0
            ],
            "scale": 0.9999945163726807
        },
        {
            "name": "Stone",
            "pos": [
                13367.509765625,
                68.72920989990235,
                12018.1142578125
            ],
            "ypr": [
                -126.23270416259766,
                -0.0,
                -0.0
            ],
            "scale": 0.9999945163726807
        },
        {
            "name": "Stone",
            "pos": [
                13367.509765625,
                68.72920989990235,
                12018.1142578125
            ],
            "ypr": [
                -126.23270416259766,
                -0.0,
                -0.0
            ],
            "scale": 0.9999945163726807
        },
        {
            "name": "Stone",
            "pos": [
                13367.509765625,
                68.72920989990235,
                12018.1142578125
            ],
            "ypr": [
                -126.23270416259766,
                -0.0,
                -0.0
            ],
            "scale": 0.9999945163726807
        },
        {
            "name": "Stone",
            "pos": [
                13367.509765625,
                68.72920989990235,
                12018.1142578125
            ],
            "ypr": [
                -126.23270416259766,
                -0.0,
                -0.0
            ],
            "scale": 0.9999945163726807
        },
        {
            "name": "Stone",
            "pos": [
                13367.509765625,
                68.72920989990235,
                12018.1142578125
            ],
            "ypr": [
                -126.23270416259766,
                -0.0,
                -0.0
            ],
            "scale": 0.9999945163726807
        },
        {
            "name": "Stone",
            "pos": [
                13367.509765625,
                68.72920989990235,
                12018.1142578125
            ],
            "ypr": [
                -126.23270416259766,
                -0.0,
                -0.0
            ],
            "scale": 0.9999945163726807
        },
        {
            "name": "Stone",
            "pos": [
                13367.509765625,
                68.72920989990235,
                12018.1142578125
            ],
            "ypr": [
                -126.23270416259766,
                -0.0,
                -0.0
            ],
            "scale": 0.9999945163726807
        },
        {
            "name": "Stone",
            "pos": [
                13367.509765625,
                68.72920989990235,
                12018.1142578125
            ],
            "ypr": [
                -126.23270416259766,
                -0.0,
                -0.0
            ],
            "scale": 0.9999945163726807
        },
        {
            "name": "Stone",
            "pos": [
                13367.509765625,
                68.72920989990235,
                12018.1142578125
            ],
            "ypr": [
                -126.23270416259766,
                -0.0,
                -0.0
            ],
            "scale": 0.9999945163726807
        },
        {
            "name": "Stone",
            "pos": [
                13367.509765625,
                68.72920989990235,
                12018.1142578125
            ],
            "ypr": [
                -126.23270416259766,
                -0.0,
                -0.0
            ],
            "scale": 0.9999945163726807
        },
        {
            "name": "Stone",
            "pos": [
                13367.509765625,
                68.72920989990235,
                12018.1142578125
            ],
            "ypr": [
                -126.23270416259766,
                -0.0,
                -0.0
            ],
            "scale": 0.9999945163726807
        },
        {
            "name": "Stone",
            "pos": [
                13367.509765625,
                68.72920989990235,
                12018.1142578125
            ],
            "ypr": [
                -126.23270416259766,
                -0.0,
                -0.0
            ],
            "scale": 0.9999945163726807
        },
        {
            "name": "Stone",
            "pos": [
                13367.509765625,
                68.72920989990235,
                12018.1142578125
            ],
            "ypr": [
                -126.23270416259766,
                -0.0,
                -0.0
            ],
            "scale": 0.9999945163726807
        },
        {
            "name": "Stone",
            "pos": [
                13367.509765625,
                68.72920989990235,
                12018.1142578125
            ],
            "ypr": [
                -126.23270416259766,
                -0.0,
                -0.0
            ],
            "scale": 0.9999945163726807
        },
        {
            "name": "Stone",
            "pos": [
                13367.509765625,
                68.72920989990235,
                12018.1142578125
            ],
            "ypr": [
                -126.23270416259766,
                -0.0,
                -0.0
            ],
            "scale": 0.9999945163726807
        },
        {
            "name": "Stone",
            "pos": [
                13367.509765625,
                68.72920989990235,
                12018.1142578125
            ],
            "ypr": [
                -126.23270416259766,
                -0.0,
                -0.0
            ],
            "scale": 0.9999945163726807
        },
        {
            "name": "Stone",
            "pos": [
                13367.509765625,
                68.72920989990235,
                12018.1142578125
            ],
            "ypr": [
                -126.23270416259766,
                -0.0,
                -0.0
            ],
            "scale": 0.9999945163726807
        },
        {
            "name": "Stone",
            "pos": [
                13367.509765625,
                68.72920989990235,
                12018.1142578125
            ],
            "ypr": [
                -126.23270416259766,
                -0.0,
                -0.0
            ],
            "scale": 0.9999945163726807
        },
        {
            "name": "Stone",
            "pos": [
                13367.509765625,
                68.72920989990235,
                12018.1142578125
            ],
            "ypr": [
                -126.23270416259766,
                -0.0,
                -0.0
            ],
            "scale": 0.9999945163726807
        },
        {
            "name": "Stone",
            "pos": [
                13367.509765625,
                68.72920989990235,
                12018.1142578125
            ],
            "ypr": [
                -126.23270416259766,
                -0.0,
                -0.0
            ],
            "scale": 0.9999945163726807
        },
        {
            "name": "Whetstone",
            "pos": [
                13367.787109375,
                69.50460052490235,
                12015.8115234375
            ],
            "ypr": [
                -108.23269653320313,
                -0.0,
                -0.0
            ],
            "scale": 0.9999934434890747
        },
        {
            "name": "Whetstone",
            "pos": [
                13367.787109375,
                69.50460052490235,
                12015.8115234375
            ],
            "ypr": [
                -108.23269653320313,
                -0.0,
                -0.0
            ],
            "scale": 0.9999934434890747
        },
        {
            "name": "Whetstone",
            "pos": [
                13367.787109375,
                69.50460052490235,
                12015.8115234375
            ],
            "ypr": [
                -108.23269653320313,
                -0.0,
                -0.0
            ],
            "scale": 0.9999934434890747
        },
        {
            "name": "Whetstone",
            "pos": [
                13367.787109375,
                69.50460052490235,
                12015.8115234375
            ],
            "ypr": [
                -108.23269653320313,
                -0.0,
                -0.0
            ],
            "scale": 0.9999934434890747
        },
        {
            "name": "Whetstone",
            "pos": [
                13367.787109375,
                69.50460052490235,
                12015.8115234375
            ],
            "ypr": [
                -108.23269653320313,
                -0.0,
                -0.0
            ],
            "scale": 0.9999934434890747
        },
        {
            "name": "Whetstone",
            "pos": [
                13367.787109375,
                69.50460052490235,
                12015.8115234375
            ],
            "ypr": [
                -108.23269653320313,
                -0.0,
                -0.0
            ],
            "scale": 0.9999934434890747
        },
        {
            "name": "Whetstone",
            "pos": [
                13367.787109375,
                69.50460052490235,
                12015.8115234375
            ],
            "ypr": [
                -108.23269653320313,
                -0.0,
                -0.0
            ],
            "scale": 0.9999934434890747
        },
        {
            "name": "Whetstone",
            "pos": [
                13367.787109375,
                69.50460052490235,
                12015.8115234375
            ],
            "ypr": [
                -108.23269653320313,
                -0.0,
                -0.0
            ],
            "scale": 0.9999934434890747
        },
        {
            "name": "SeaChest",
            "pos": [
                13367.43359375,
                68.72118377685547,
                12017.2421875
            ],
            "ypr": [
                -0.23266610503196717,
                0.734582781791687,
                0.08061676472425461
            ],
            "scale": 0.9999963045120239
        },
        {
            "name": "SeaChest",
            "pos": [
                13367.43359375,
                68.72118377685547,
                12017.2421875
            ],
            "ypr": [
                -0.23266586661338807,
                0.7345383167266846,
                0.08061672002077103
            ],
            "scale": 0.9999956488609314
        },
        {
            "name": "SeaChest",
            "pos": [
                13367.43359375,
                68.72118377685547,
                12017.2421875
            ],
            "ypr": [
                -0.23266659677028657,
                0.7345165014266968,
                0.08061680942773819
            ],
            "scale": 0.9999955296516419
        },
        {
            "name": "SeaChest",
            "pos": [
                13367.43359375,
                68.72118377685547,
                12017.2421875
            ],
            "ypr": [
                -0.23266610503196717,
                0.7345401048660278,
                0.0806167796254158
            ],
            "scale": 0.999997079372406
        },
        {
            "name": "SeaChest",
            "pos": [
                13367.43359375,
                68.72118377685547,
                12017.2421875
            ],
            "ypr": [
                -0.23266445100307465,
                0.7345104217529297,
                0.08061674982309342
            ],
            "scale": 0.9999966025352478
        },
        {
            "name": "SeaChest",
            "pos": [
                13367.43359375,
                68.72118377685547,
                12017.2421875
            ],
            "ypr": [
                -0.2326127290725708,
                0.7344835996627808,
                0.08061673492193222
            ],
            "scale": 0.9999964237213135
        },
        {
            "name": "SeaChest",
            "pos": [
                13367.43359375,
                68.72118377685547,
                12017.2421875
            ],
            "ypr": [
                -0.23266538977622987,
                0.7344715595245361,
                0.08061674982309342
            ],
            "scale": 0.9999966025352478
        },
        {
            "name": "Barrel_Green",
            "pos": [
                13367.619140625,
                68.7490463256836,
                12012.302734375
            ],
            "ypr": [
                -126.23269653320313,
                -0.09159950911998749,
                0.1833849996328354
            ],
            "scale": 0.9999926686286926
        },
        {
            "name": "Barrel_Green",
            "pos": [
                13367.619140625,
                68.7490463256836,
                12012.302734375
            ],
            "ypr": [
                -126.23269653320313,
                -0.09159904718399048,
                0.1833849996328354
            ],
            "scale": 0.9999925494194031
        },
        {
            "name": "Barrel_Green",
            "pos": [
                13367.619140625,
                68.7490463256836,
                12012.302734375
            ],
            "ypr": [
                -126.23269653320313,
                -0.09159884601831436,
                0.1833849996328354
            ],
            "scale": 0.9999924302101135
        },
        {
            "name": "Barrel_Green",
            "pos": [
                13367.619140625,
                68.7490463256836,
                12012.302734375
            ],
            "ypr": [
                -126.23268127441406,
                -0.09159936010837555,
                0.1833849996328354
            ],
            "scale": 0.999992847442627
        },
        {
            "name": "Barrel_Blue",
            "pos": [
                13367.7275390625,
                68.75057220458985,
                12011.57421875
            ],
            "ypr": [
                -126.23269653320313,
                -0.09159950911998749,
                0.1833849996328354
            ],
            "scale": 0.9999926686286926
        },
        {
            "name": "Barrel_Blue",
            "pos": [
                13367.7275390625,
                68.75057220458985,
                12011.57421875
            ],
            "ypr": [
                -126.23269653320313,
                -0.09159904718399048,
                0.1833849996328354
            ],
            "scale": 0.9999925494194031
        },
        {
            "name": "Barrel_Red",
            "pos": [
                13367.5380859375,
                68.75142669677735,
                12010.6923828125
            ],
            "ypr": [
                -126.23269653320313,
                -0.09159950911998749,
                0.1833849996328354
            ],
            "scale": 0.9999926686286926
        },
        {
            "name": "Barrel_Red",
            "pos": [
                13367.5380859375,
                68.75142669677735,
                12010.6923828125
            ],
            "ypr": [
                -126.23269653320313,
                -0.09159904718399048,
                0.1833849996328354
            ],
            "scale": 0.9999925494194031
        },
        {
            "name": "Barrel_Red",
            "pos": [
                13367.5380859375,
                68.75142669677735,
                12010.6923828125
            ],
            "ypr": [
                -126.23269653320313,
                -0.09159884601831436,
                0.1833849996328354
            ],
            "scale": 0.9999924302101135
        },
        {
            "name": "Barrel_Red",
            "pos": [
                13367.5380859375,
                68.75142669677735,
                12010.6923828125
            ],
            "ypr": [
                -126.23268127441406,
                -0.09159936010837555,
                0.1833849996328354
            ],
            "scale": 0.999992847442627
        },
        {
            "name": "Flag_BrainZ",
            "pos": [
                13372.0185546875,
                66.12743377685547,
                12034.0986328125
            ],
            "ypr": [
                35.9999885559082,
                -0.0,
                -0.0
            ],
            "scale": 0.9999996423721314
        },
        {
            "name": "BakedBeansCan_Opened",
            "pos": [
                13381.55078125,
                69.98052978515625,
                12034.0224609375
            ],
            "ypr": [
                0.0,
                -0.0,
                -0.0
            ],
            "scale": 0.9999998211860657
        },
        {
            "name": "BakedBeansCan_Opened",
            "pos": [
                13381.55078125,
                69.98052978515625,
                12034.0224609375
            ],
            "ypr": [
                0.0,
                -0.0,
                -0.0
            ],
            "scale": 0.9999997615814209
        },
        {
            "name": "BakedBeansCan_Opened",
            "pos": [
                13381.55078125,
                69.98052978515625,
                12034.0224609375
            ],
            "ypr": [
                0.0,
                -0.0,
                -0.0
            ],
            "scale": 0.9999996423721314
        },
        {
            "name": "SodaCan_Pipsi",
            "pos": [
                13380.12890625,
                70.04529571533203,
                12035.7861328125
            ],
            "ypr": [
                138.8403778076172,
                -0.0,
                -0.0
            ],
            "scale": 0.9999942779541016
        },
        {
            "name": "SodaCan_Pipsi",
            "pos": [
                13380.12890625,
                70.04529571533203,
                12035.7861328125
            ],
            "ypr": [
                138.8403778076172,
                -0.0,
                -0.0
            ],
            "scale": 0.9999947547912598
        },
        {
            "name": "SodaCan_Pipsi",
            "pos": [
                13380.12890625,
                70.04529571533203,
                12035.7861328125
            ],
            "ypr": [
                138.8403778076172,
                -0.0,
                -0.0
            ],
            "scale": 0.9999947547912598
        },
        {
            "name": "SodaCan_Pipsi",
            "pos": [
                13380.12890625,
                70.04529571533203,
                12035.7861328125
            ],
            "ypr": [
                138.8403778076172,
                -0.0,
                -0.0
            ],
            "scale": 0.9999947547912598
        },
        {
            "name": "SodaCan_Pipsi",
            "pos": [
                13380.12890625,
                70.04529571533203,
                12035.7861328125
            ],
            "ypr": [
                138.84033203125,
                -0.0,
                -0.0
            ],
            "scale": 0.9999940395355225
        },
        {
            "name": "BakedBeansCan_Opened",
            "pos": [
                13381.55078125,
                69.98052978515625,
                12034.0224609375
            ],
            "ypr": [
                0.0,
                -0.0,
                -0.0
            ],
            "scale": 0.9999995231628418
        },
        {
            "name": "TacticalBaconCan_Opened",
            "pos": [
                13381.611328125,
                69.95944213867188,
                12033.078125
            ],
            "ypr": [
                0.0,
                -0.0,
                -0.0
            ],
            "scale": 0.9999998211860657
        },
        {
            "name": "TacticalBaconCan_Opened",
            "pos": [
                13381.611328125,
                69.95944213867188,
                12033.078125
            ],
            "ypr": [
                0.0,
                -0.0,
                -0.0
            ],
            "scale": 0.9999997615814209
        },
        {
            "name": "TacticalBaconCan_Opened",
            "pos": [
                13381.611328125,
                69.95944213867188,
                12033.078125
            ],
            "ypr": [
                0.0,
                -0.0,
                -0.0
            ],
            "scale": 0.9999996423721314
        },
        {
            "name": "CombatKnife",
            "pos": [
                13379.439453125,
                70.06973266601563,
                12036.4609375
            ],
            "ypr": [
                0.0,
                -0.0,
                -0.0
            ],
            "scale": 0.9999998807907105
        },
        {
            "name": "ChernarusMap",
            "pos": [
                13379.6884765625,
                70.09009552001953,
                12035.93359375
            ],
            "ypr": [
                0.0,
                -0.0,
                -0.0
            ],
            "scale": 0.9999998807907105
        },
        {
            "name": "NylonKnifeSheath",
            "pos": [
                13379.529296875,
                70.01094055175781,
                12035.8740234375
            ],
            "ypr": [
                0.0,
                -0.0,
                -0.0
            ],
            "scale": 0.9999998807907105
        },
        {
            "name": "HikingJacket_Red",
            "pos": [
                13385.857421875,
                72.77424621582031,
                12034.8876953125
            ],
            "ypr": [
                -1.3655508756637574,
                -0.0,
                -0.0
            ],
            "scale": 0.9999812841415405
        },
        {
            "name": "DarkMotoHelmet_YellowScarred",
            "pos": [
                13387.4267578125,
                72.3221435546875,
                12030.037109375
            ],
            "ypr": [
                -75.96361541748047,
                -0.0,
                -0.0
            ],
            "scale": 0.9999963045120239
        },
        {
            "name": "CargoPants_Black",
            "pos": [
                13385.978515625,
                72.77803039550781,
                12035.3935546875
            ],
            "ypr": [
                9.0,
                -0.0,
                -0.0
            ],
            "scale": 1.0
        },
        {
            "name": "PlateCarrierVest_Black",
            "pos": [
                13385.982421875,
                72.7212142944336,
                12034.0859375
            ],
            "ypr": [
                -1.3655508756637574,
                -0.0,
                -0.0
            ],
            "scale": 0.9999812841415405
        },
        {
            "name": "PlateCarrierHolster_Black",
            "pos": [
                13386.05859375,
                72.77083587646485,
                12034.509765625
            ],
            "ypr": [
                99.87755584716797,
                -0.0,
                -0.0
            ],
            "scale": 0.9999998807907105
        },
        {
            "name": "PlateCarrierPouches_Black",
            "pos": [
                13386.0419921875,
                72.75494384765625,
                12034.4501953125
            ],
            "ypr": [
                0.0,
                -0.0,
                -0.0
            ],
            "scale": 0.9999998807907105
        },
        {
            "name": "MilitaryBoots_Black",
            "pos": [
                13385.9521484375,
                73.24783325195313,
                12035.0361328125
            ],
            "ypr": [
                -1.3655508756637574,
                -0.0,
                -0.0
            ],
            "scale": 0.9999812841415405
        },
        {
            "name": "TacticalGloves_Black",
            "pos": [
                13385.9580078125,
                72.76557159423828,
                12033.060546875
            ],
            "ypr": [
                65.12239074707031,
                -0.0,
                -0.0
            ],
            "scale": 0.9999891519546509
        },
        {
            "name": "NVGoggles",
            "pos": [
                13386.2373046875,
                72.8282470703125,
                12033.572265625
            ],
            "ypr": [
                87.98969268798828,
                -0.0,
                -0.0
            ],
            "scale": 0.9999992847442627
        },
        {
            "name": "NVGHeadstrap",
            "pos": [
                13385.947265625,
                72.72607421875,
                12033.3662109375
            ],
            "ypr": [
                100.82228088378906,
                -0.0,
                -0.0
            ],
            "scale": 0.9999994039535523
        },
        {
            "name": "Battery9V",
            "pos": [
                13386.2099609375,
                72.7417221069336,
                12033.7548828125
            ],
            "ypr": [
                -1.3655508756637574,
                -0.0,
                -0.0
            ],
            "scale": 0.9999812841415405
        },
        {
            "name": "Battery9V",
            "pos": [
                13386.2099609375,
                72.7417221069336,
                12033.7548828125
            ],
            "ypr": [
                -1.3655508756637574,
                -0.0,
                -0.0
            ],
            "scale": 0.9999812841415405
        },
        {
            "name": "Battery9V",
            "pos": [
                13386.2099609375,
                72.7417221069336,
                12033.7548828125
            ],
            "ypr": [
                -1.3655508756637574,
                -0.0,
                -0.0
            ],
            "scale": 0.9999812841415405
        },
        {
            "name": "Battery9V",
            "pos": [
                13386.2099609375,
                72.7417221069336,
                12033.7548828125
            ],
            "ypr": [
                -1.3655508756637574,
                -0.0,
                -0.0
            ],
            "scale": 0.9999812841415405
        },
        {
            "name": "Battery9V",
            "pos": [
                13386.2099609375,
                72.7417221069336,
                12033.7548828125
            ],
            "ypr": [
                -1.3655508756637574,
                -0.0,
                -0.0
            ],
            "scale": 0.9999812841415405
        },
        {
            "name": "Battery9V",
            "pos": [
                13386.2099609375,
                72.7417221069336,
                12033.7548828125
            ],
            "ypr": [
                -1.3655508756637574,
                -0.0,
                -0.0
            ],
            "scale": 0.9999812841415405
        },
        {
            "name": "Battery9V",
            "pos": [
                13386.2099609375,
                72.7417221069336,
                12033.7548828125
            ],
            "ypr": [
                -1.3654285669326783,
                -0.0,
                -0.0
            ],
            "scale": 0.9999855756759644
        },
        {
            "name": "M4A1_Black",
            "pos": [
                13387.6943359375,
                70.32553100585938,
                12029.8701171875
            ],
            "ypr": [
                0.0,
                -0.0,
                -0.0
            ],
            "scale": 0.9999998807907105
        },
        {
            "name": "M4_MPBttstck",
            "pos": [
                13387.3828125,
                69.9511947631836,
                12030.078125
            ],
            "ypr": [
                0.0,
                -0.0,
                -0.0
            ],
            "scale": 0.9999998807907105
        },
        {
            "name": "M4_RISHndgrd_Black",
            "pos": [
                13387.5126953125,
                69.96085357666016,
                12030.1435546875
            ],
            "ypr": [
                -6.223387718200684,
                -0.0,
                -0.0
            ],
            "scale": 0.9999998807907105
        },
        {
            "name": "ReflexOptic",
            "pos": [
                13387.6298828125,
                69.97392272949219,
                12030.3330078125
            ],
            "ypr": [
                0.0,
                -0.0,
                -0.0
            ],
            "scale": 0.9999998807907105
        },
        {
            "name": "M4_Suppressor",
            "pos": [
                13387.4853515625,
                69.96224975585938,
                12030.427734375
            ],
            "ypr": [
                0.0,
                -0.0,
                -0.0
            ],
            "scale": 0.9999998807907105
        },
        {
            "name": "M4_Suppressor",
            "pos": [
                13387.4853515625,
                69.96224975585938,
                12030.427734375
            ],
            "ypr": [
                0.0,
                -0.0,
                -0.0
            ],
            "scale": 0.9999998211860657
        },
        {
            "name": "Mag_STANAG_60Rnd",
            "pos": [
                13387.849609375,
                70.0639419555664,
                12030.025390625
            ],
            "ypr": [
                0.0,
                -0.0,
                -0.0
            ],
            "scale": 0.9999998807907105
        },
        {
            "name": "Mag_STANAG_60Rnd",
            "pos": [
                13387.849609375,
                70.0639419555664,
                12030.025390625
            ],
            "ypr": [
                0.0,
                -0.0,
                -0.0
            ],
            "scale": 0.9999998211860657
        },
        {
            "name": "Mag_STANAG_60Rnd",
            "pos": [
                13387.849609375,
                70.0639419555664,
                12030.025390625
            ],
            "ypr": [
                0.0,
                -0.0,
                -0.0
            ],
            "scale": 0.9999997615814209
        },
        {
            "name": "Mag_STANAG_60Rnd",
            "pos": [
                13387.849609375,
                70.0639419555664,
                12030.025390625
            ],
            "ypr": [
                0.0,
                -0.0,
                -0.0
            ],
            "scale": 0.9999996423721314
        },
        {
            "name": "Winchester70_Black",
            "pos": [
                13386.7939453125,
                70.42353057861328,
                12029.869140625
            ],
            "ypr": [
                0.0,
                -0.0,
                -0.0
            ],
            "scale": 0.9999998807907105
        },
        {
            "name": "HuntingOptic",
            "pos": [
                13387.84765625,
                70.06027221679688,
                12030.8642578125
            ],
            "ypr": [
                0.0,
                -0.0,
                -0.0
            ],
            "scale": 0.9999998807907105
        },
        {
            "name": "Ammo_308Win",
            "pos": [
                13387.7138671875,
                69.94048309326172,
                12030.7373046875
            ],
            "ypr": [
                0.0,
                -0.0,
                -0.0
            ],
            "scale": 0.9999998807907105
        },
        {
            "name": "Ammo_308Win",
            "pos": [
                13387.7138671875,
                69.94048309326172,
                12030.7373046875
            ],
            "ypr": [
                0.0,
                -0.0,
                -0.0
            ],
            "scale": 0.9999998211860657
        },
        {
            "name": "Ammo_308Win",
            "pos": [
                13387.7138671875,
                69.94048309326172,
                12030.7373046875
            ],
            "ypr": [
                0.0,
                -0.0,
                -0.0
            ],
            "scale": 0.9999997615814209
        },
        {
            "name": "Ammo_308Win",
            "pos": [
                13387.7138671875,
                69.94048309326172,
                12030.7373046875
            ],
            "ypr": [
                0.0,
                -0.0,
                -0.0
            ],
            "scale": 0.9999996423721314
        },
        {
            "name": "Ammo_308Win",
            "pos": [
                13387.7138671875,
                69.94048309326172,
                12030.7373046875
            ],
            "ypr": [
                0.0,
                -0.0,
                -0.0
            ],
            "scale": 0.9999995827674866
        },
        {
            "name": "Ammo_308Win",
            "pos": [
                13387.7138671875,
                69.94048309326172,
                12030.7373046875
            ],
            "ypr": [
                0.0,
                -0.0,
                -0.0
            ],
            "scale": 0.9999995231628418
        },
        {
            "name": "Ammo_308Win",
            "pos": [
                13387.7138671875,
                69.94048309326172,
                12030.7373046875
            ],
            "ypr": [
                0.0,
                -0.0,
                -0.0
            ],
            "scale": 0.9999994039535523
        },
        {
            "name": "Ammo_308Win",
            "pos": [
                13387.7138671875,
                69.94048309326172,
                12030.7373046875
            ],
            "ypr": [
                0.0,
                -0.0,
                -0.0
            ],
            "scale": 0.9999993443489075
        },
        {
            "name": "Ammo_308Win",
            "pos": [
                13387.7138671875,
                69.94048309326172,
                12030.7373046875
            ],
            "ypr": [
                0.0,
                -0.0,
                -0.0
            ],
            "scale": 0.9999992847442627
        },
        {
            "name": "Engraved1911",
            "pos": [
                13386.6220703125,
                70.30970764160156,
                12029.873046875
            ],
            "ypr": [
                0.0,
                -0.0,
                -0.0
            ],
            "scale": 0.9999998807907105
        },
        {
            "name": "Mag_1911_7Rnd",
            "pos": [
                13387.369140625,
                69.9714126586914,
                12030.853515625
            ],
            "ypr": [
                0.0,
                -0.0,
                -0.0
            ],
            "scale": 0.9999998807907105
        },
        {
            "name": "Mag_1911_7Rnd",
            "pos": [
                13387.369140625,
                69.9714126586914,
                12030.853515625
            ],
            "ypr": [
                0.0,
                -0.0,
                -0.0
            ],
            "scale": 0.9999998211860657
        },
        {
            "name": "Mag_1911_7Rnd",
            "pos": [
                13387.369140625,
                69.9714126586914,
                12030.853515625
            ],
            "ypr": [
                0.0,
                -0.0,
                -0.0
            ],
            "scale": 0.9999997615814209
        },
        {
            "name": "Mag_1911_7Rnd",
            "pos": [
                13387.369140625,
                69.9714126586914,
                12030.853515625
            ],
            "ypr": [
                0.0,
                -0.0,
                -0.0
            ],
            "scale": 0.9999996423721314
        },
        {
            "name": "Mag_1911_7Rnd",
            "pos": [
                13387.369140625,
                69.9714126586914,
                12030.853515625
            ],
            "ypr": [
                0.0,
                -0.0,
                -0.0
            ],
            "scale": 0.9999995827674866
        },
        {
            "name": "Mag_1911_7Rnd",
            "pos": [
                13387.369140625,
                69.9714126586914,
                12030.853515625
            ],
            "ypr": [
                0.0,
                -0.0,
                -0.0
            ],
            "scale": 0.9999995231628418
        },
        {
            "name": "Mag_1911_7Rnd",
            "pos": [
                13387.369140625,
                69.9714126586914,
                12030.853515625
            ],
            "ypr": [
                0.0,
                -0.0,
                -0.0
            ],
            "scale": 0.9999994039535523
        },
        {
            "name": "Mag_1911_7Rnd",
            "pos": [
                13387.369140625,
                69.9714126586914,
                12030.853515625
            ],
            "ypr": [
                0.0,
                -0.0,
                -0.0
            ],
            "scale": 0.9999993443489075
        },
        {
            "name": "Pliers",
            "pos": [
                13367.76171875,
                69.76197814941406,
                12014.6279296875
            ],
            "ypr": [
                172.05995178222657,
                -0.0,
                -0.0
            ],
            "scale": 0.9999953508377075
        },
        {
            "name": "Pliers",
            "pos": [
                13367.76171875,
                69.76197814941406,
                12014.6279296875
            ],
            "ypr": [
                172.05995178222657,
                -0.0,
                -0.0
            ],
            "scale": 0.9999953508377075
        },
        {
            "name": "Pliers",
            "pos": [
                13367.76171875,
                69.76197814941406,
                12014.6279296875
            ],
            "ypr": [
                172.05995178222657,
                -0.0,
                -0.0
            ],
            "scale": 0.9999953508377075
        },
        {
            "name": "Pliers",
            "pos": [
                13367.76171875,
                69.76197814941406,
                12014.6279296875
            ],
            "ypr": [
                172.05995178222657,
                -0.0,
                -0.0
            ],
            "scale": 0.9999953508377075
        },
        {
            "name": "Pliers",
            "pos": [
                13367.76171875,
                69.76197814941406,
                12014.6279296875
            ],
            "ypr": [
                172.05995178222657,
                -0.0,
                -0.0
            ],
            "scale": 0.9999952912330627
        },
        {
            "name": "Pliers",
            "pos": [
                13367.76171875,
                69.76197814941406,
                12014.6279296875
            ],
            "ypr": [
                172.05995178222657,
                -0.0,
                -0.0
            ],
            "scale": 0.9999952912330627
        },
        {
            "name": "Pliers",
            "pos": [
                13367.76171875,
                69.76197814941406,
                12014.6279296875
            ],
            "ypr": [
                172.05995178222657,
                -0.0,
                -0.0
            ],
            "scale": 0.999994695186615
        },
        {
            "name": "Stone",
            "pos": [
                13367.509765625,
                68.72920989990235,
                12018.1142578125
            ],
            "ypr": [
                -126.23269653320313,
                -0.0,
                -0.0
            ],
            "scale": 0.9999943971633911
        },
        {
            "name": "Stone",
            "pos": [
                13367.509765625,
                68.72920989990235,
                12018.1142578125
            ],
            "ypr": [
                -126.23269653320313,
                -0.0,
                -0.0
            ],
            "scale": 0.9999942779541016
        },
        {
            "name": "Stone",
            "pos": [
                13367.509765625,
                68.72920989990235,
                12018.1142578125
            ],
            "ypr": [
                -126.23269653320313,
                -0.0,
                -0.0
            ],
            "scale": 0.999994158744812
        },
        {
            "name": "Stone",
            "pos": [
                13367.509765625,
                68.72920989990235,
                12018.1142578125
            ],
            "ypr": [
                -126.23269653320313,
                -0.0,
                -0.0
            ],
            "scale": 0.9999940395355225
        },
        {
            "name": "Stone",
            "pos": [
                13367.509765625,
                68.72920989990235,
                12018.1142578125
            ],
            "ypr": [
                -126.23269653320313,
                -0.0,
                -0.0
            ],
            "scale": 0.9999939203262329
        },
        {
            "name": "Stone",
            "pos": [
                13367.509765625,
                68.72920989990235,
                12018.1142578125
            ],
            "ypr": [
                -126.23269653320313,
                -0.0,
                -0.0
            ],
            "scale": 0.9999938011169434
        },
        {
            "name": "Stone",
            "pos": [
                13367.509765625,
                68.72920989990235,
                12018.1142578125
            ],
            "ypr": [
                -126.23269653320313,
                -0.0,
                -0.0
            ],
            "scale": 0.9999936819076538
        },
        {
            "name": "LargeTent",
            "pos": [
                13368.875,
                68.55947875976563,
                12013.083984375
            ],
            "ypr": [
                0.0,
                -0.0,
                -0.0
            ],
            "scale": 0.9999998807907105
        },
        {
            "name": "LargeTent",
            "pos": [
                13368.875,
                68.55947875976563,
                12013.083984375
            ],
            "ypr": [
                0.0,
                -0.0,
                -0.0
            ],
            "scale": 0.9999998211860657
        },
        {
            "name": "LargeTent",
            "pos": [
                13368.875,
                68.55947875976563,
                12013.083984375
            ],
            "ypr": [
                0.0,
                -0.0,
                -0.0
            ],
            "scale": 0.9999997615814209
        },
        {
            "name": "WoodenLog",
            "pos": [
                13367.95703125,
                68.5368881225586,
                12030.322265625
            ],
            "ypr": [
                4.4860968589782719,
                -0.0,
                -0.0
            ],
            "scale": 0.9999983310699463
        },
        {
            "name": "WoodenLog",
            "pos": [
                13367.95703125,
                68.5368881225586,
                12030.322265625
            ],
            "ypr": [
                4.486096382141113,
                -0.0,
                -0.0
            ],
            "scale": 0.9999982118606567
        },
        {
            "name": "WoodenLog",
            "pos": [
                13367.95703125,
                68.5368881225586,
                12030.322265625
            ],
            "ypr": [
                4.486096382141113,
                -0.0,
                -0.0
            ],
            "scale": 0.9999980926513672
        },
        {
            "name": "WoodenLog",
            "pos": [
                13367.95703125,
                68.5368881225586,
                12030.322265625
            ],
            "ypr": [
                4.486096382141113,
                -0.0,
                -0.0
            ],
            "scale": 0.9999979734420776
        },
        {
            "name": "WitchHood_Red",
            "pos": [
                13387.2822265625,
                73.15592956542969,
                12029.869140625
            ],
            "ypr": [
                0.0,
                -0.0,
                -0.0
            ],
            "scale": 0.9999998807907105
        },
        {
            "name": "Lockpick",
            "pos": [
                13367.5947265625,
                69.51148223876953,
                12015.8857421875
            ],
            "ypr": [
                0.0,
                -0.0,
                -0.0
            ],
            "scale": 0.9999998807907105
        },
        {
            "name": "CombinationLock4",
            "pos": [
                13367.802734375,
                69.59617614746094,
                12016.2138671875
            ],
            "ypr": [
                0.0,
                -0.0,
                -0.0
            ],
            "scale": 0.9999998807907105
        }
    ]
}